isoc_airbyte_transformations/__init__.py
isoc_airbyte_transformations/main.py
isoc_airbyte_transformations/transformers/__init__.py
isoc_airbyte_transformations/transformers/dimensions_transformer.py
isoc_airbyte_transformations/transformers/generic_transformer.py
isoc_airbyte_transformations/transformers/metrics_transformer.py
isoc_airbyte_transformations-0.1.0.dist-info/licenses/LICENSE
isoc_airbyte_transformations-0.1.0.dist-info/METADATA
isoc_airbyte_transformations-0.1.0.dist-info/WHEEL
isoc_airbyte_transformations-0.1.0.dist-info/top_level.txt
isoc_airbyte_transformations-0.1.0.dist-info/RECORD
