Metadata-Version: 2.4
Name: isoc_airbyte_transformations
Version: 0.1.0
Summary: A simple transformations utility package
Author: Softroniclabs Pvt Ltd
License: MIT
Classifier: Programming Language :: Python :: 3
Requires-Python: >=3.6
License-File: LICENSE
Dynamic: license-file
